setup.cfg
setup.py
cbtestlib/EC2.py
cbtestlib/__init__.py
cbtestlib/cli_interface.py
cbtestlib/crc32.py
cbtestlib/exception.py
cbtestlib/load_runner.py
cbtestlib/logger.py
cbtestlib/mc_ascii_client.py
cbtestlib/mc_bin_client.py
cbtestlib/mc_bin_server.py
cbtestlib/memcacheConstants.py
cbtestlib/results_helper.py
cbtestlib/tap.py
cbtestlib/testconstants.py
cbtestlib/testrunner_common.py
cbtestlib/xunit.py
cbtestlib.egg-info/PKG-INFO
cbtestlib.egg-info/SOURCES.txt
cbtestlib.egg-info/dependency_links.txt
cbtestlib.egg-info/requires.txt
cbtestlib.egg-info/top_level.txt
cbtestlib/builds/BeautifulSoup.py
cbtestlib/builds/__init__.py
cbtestlib/builds/build_query.py
cbtestlib/cbkarma/__init__.py
cbtestlib/cbkarma/rest_client.py
cbtestlib/couchbase/__init__.py
cbtestlib/couchbase/cluster.py
cbtestlib/couchbase/document.py
cbtestlib/couchbase/documentgenerator.py
cbtestlib/couchbase/stats_tools.py
cbtestlib/couchbase/view_helper.py
cbtestlib/couchdb/__init__.py
cbtestlib/couchdb/client.py
cbtestlib/couchdb/design.py
cbtestlib/couchdb/http.py
cbtestlib/couchdb/json.py
cbtestlib/couchdb/mapping.py
cbtestlib/couchdb/multipart.py
cbtestlib/couchdb/view.py
cbtestlib/membase/__init__.py
cbtestlib/membase/api/__init__.py
cbtestlib/membase/api/exception.py
cbtestlib/membase/api/mimeTypes.py
cbtestlib/membase/api/rest_client.py
cbtestlib/membase/api/tap.py
cbtestlib/membase/api/httplib2/__init__.py
cbtestlib/membase/api/httplib2/iri2uri.py
cbtestlib/membase/helper/__init__.py
cbtestlib/membase/helper/bucket_helper.py
cbtestlib/membase/helper/checkpoints.py
cbtestlib/membase/helper/cluster_helper.py
cbtestlib/membase/helper/failover_helper.py
cbtestlib/membase/helper/rebalance_helper.py
cbtestlib/membase/helper/spatial_helper.py
cbtestlib/membase/helper/stats.py
cbtestlib/membase/performance/__init__.py
cbtestlib/membase/performance/stats.py
cbtestlib/memcached/__init__.py
cbtestlib/memcached/helper/__init__.py
cbtestlib/memcached/helper/data_helper.py
cbtestlib/memcached/helper/kvstore.py
cbtestlib/memcached/helper/old_kvstore.py
cbtestlib/perf_engines/__init__.py
cbtestlib/perf_engines/cbsoda.py
cbtestlib/perf_engines/mcsoda.py
