Metadata-Version: 1.0
Name: cbtestlib
Version: 1.0.0
Summary: Couchbase test library
Home-page: http://www.couchbase.com/
Author: Couchbase Inc
Author-email: build@couchbase.com
License: UNKNOWN
Keywords: encoding,i18n,xml
Platform: UNKNOWN
Classifier: Programming Language :: Python
Classifier: Programming Language :: Python :: 2.6
Classifier: Development Status :: 5 - Production/Stable
Classifier: Environment :: Other Environment
Classifier: Intended Audience :: Developers
Classifier: License :: OSI Approved :: Apache Software License
Classifier: Operating System :: OS Independent
Classifier: Topic :: Software Development :: Libraries :: Python Modules
